<?xml version="1.0" encoding="utf-16"?>
<EasyQuestProfile xmlns:xsi="http://www.w3.org/2001/XMLSchema-instance" xmlns:xsd="http://www.w3.org/2001/XMLSchema">
  <QuestsSorted>
    <QuestsSorted Action="WriteLog" NameClass="=== Start Lunar Festival - Eastern Kingdoms ===" />
    <QuestsSorted Action="Pulse" NameClass="ToEasternKingdoms" />
    <QuestsSorted Action="None" NameClass="ObjectManager.Me.IsHorde" />
    <QuestsSorted Action="Pulse" NameClass="TimeTravellingBlastedLands" />
    <QuestsSorted Action="TurnIn" NameClass="BellowragetheElder" />
    <QuestsSorted Action="TurnIn" NameClass="StargladetheElder" />
    <QuestsSorted Action="TurnIn" NameClass="WinterhooftheElder" />
    <QuestsSorted Action="TurnIn" NameClass="SkychasertheElder" />
    <QuestsSorted Action="TurnIn" NameClass="StormbrowtheElder" />
    <QuestsSorted Action="TurnIn" NameClass="HammershouttheElder" />
    <QuestsSorted Action="TurnIn" NameClass="RumblerocktheElder" />
    <QuestsSorted Action="TurnIn" NameClass="DawnstridertheElder" />
    <QuestsSorted Action="TurnIn" NameClass="GoldwelltheElder" />
    <QuestsSorted Action="TurnIn" NameClass="SilverveintheElder" />
    <QuestsSorted Action="TurnIn" NameClass="FirebeardtheElder" />
    <QuestsSorted Action="TurnIn" NameClass="DarkfeathertheElder" />
    <QuestsSorted Action="TurnIn" NameClass="HighpeaktheElder" />
    <QuestsSorted Action="TurnIn" NameClass="SnowcrowntheElder" />
    <QuestsSorted Action="None" NameClass="" />
    <QuestsSorted Action="TurnIn" NameClass="MoonstriketheElder" />
    <QuestsSorted Action="None" NameClass="" />
    <QuestsSorted Action="TurnIn" NameClass="GraveborntheElder" />
    <QuestsSorted Action="TurnIn" NameClass="DarkcoretheElder" />
    <QuestsSorted Action="TurnIn" NameClass="ObsidiantheElder" />
    <QuestsSorted Action="WriteLog" NameClass="=== Complete Lunar Festival - Eastern Kingdoms ===" />
  </QuestsSorted>
  <NpcQuest>
    <NPCQuest Id="15563" Name="Предок Грозояр" GameObject="false">
      <PickUpQuests />
      <TurnInQuests>
        <int>8647</int>
      </TurnInQuests>
      <Position X="-11791.84" Y="-3181.733" Z="-30.16162" Type="Flying" />
    </NPCQuest>
    <NPCQuest Id="15596" Name="Предок Звездный Луг" GameObject="false">
      <PickUpQuests />
      <TurnInQuests>
        <int>8716</int>
      </TurnInQuests>
      <Position X="-11954.22" Y="-1168.817" Z="77.66743" Type="Flying" />
    </NPCQuest>
    <NPCQuest Id="15576" Name="Предок Заиндевевшее Копыто" GameObject="false">
      <PickUpQuests />
      <TurnInQuests>
        <int>8674</int>
      </TurnInQuests>
      <Position X="-14424.64" Y="531.7743" Z="24.79767" Type="Flying" />
    </NPCQuest>
    <NPCQuest Id="15577" Name="Предок Небесная Охотница" GameObject="false">
      <PickUpQuests />
      <TurnInQuests>
        <int>8675</int>
      </TurnInQuests>
      <Position X="-10498.71" Y="1034.053" Z="95.61404" Type="Flying" />
    </NPCQuest>
    <NPCQuest Id="15565" Name="Предок Штормоскал" GameObject="false">
      <PickUpQuests />
      <TurnInQuests>
        <int>8649</int>
      </TurnInQuests>
      <Position X="-9413.271" Y="154.2857" Z="57.07288" Type="Flying" />
    </NPCQuest>
    <NPCQuest Id="15562" Name="Предок Молотозвон" GameObject="false">
      <PickUpQuests />
      <TurnInQuests>
        <int>8646</int>
      </TurnInQuests>
      <Position X="-9102.79" Y="335.882" Z="94.03621" Type="Flying" />
    </NPCQuest>
    <NPCQuest Id="15557" Name="Предок Скалогром" GameObject="false">
      <PickUpQuests />
      <TurnInQuests>
        <int>8636</int>
      </TurnInQuests>
      <Position X="-7938.574" Y="-2674.642" Z="209.1428" Type="Flying" />
    </NPCQuest>
    <NPCQuest Id="15585" Name="Предок Рассветная Странница" GameObject="false">
      <PickUpQuests />
      <TurnInQuests>
        <int>8683</int>
      </TurnInQuests>
      <Position X="-7487.946" Y="-2115.595" Z="137.767" Type="Flying" />
    </NPCQuest>
    <NPCQuest Id="15569" Name="Предок Златокладезь" GameObject="false">
      <PickUpQuests />
      <TurnInQuests>
        <int>8653</int>
      </TurnInQuests>
      <Position X="-5571.175" Y="-502.7326" Z="402.8977" Type="Flying" />
    </NPCQuest>
    <NPCQuest Id="15558" Name="Предок Среброжил" GameObject="false">
      <PickUpQuests />
      <TurnInQuests>
        <int>8642</int>
      </TurnInQuests>
      <Position X="-5343.725" Y="-2912.939" Z="345.1075" Type="Flying" />
    </NPCQuest>
    <NPCQuest Id="55219" Name="Предок Огнебород" GameObject="false">
      <PickUpQuests />
      <TurnInQuests>
        <int>29737</int>
      </TurnInQuests>
      <Position X="-4632.29" Y="-5120.853" Z="124.2168" Type="Flying" />
    </NPCQuest>
    <NPCQuest Id="55218" Name="Предок Темное Перо" GameObject="false">
      <PickUpQuests />
      <TurnInQuests>
        <int>29736</int>
      </TurnInQuests>
      <Position X="-3318.38" Y="-5172.05" Z="79.14178" Type="Flying" />
    </NPCQuest>
    <NPCQuest Id="15559" Name="Предок Крутой Утес" GameObject="false">
      <PickUpQuests />
      <TurnInQuests>
        <int>8643</int>
      </TurnInQuests>
      <Position X="233.4556" Y="-3499.973" Z="160.9503" Type="Flying" />
    </NPCQuest>
    <NPCQuest Id="15566" Name="Предок Снежнокрон" GameObject="false">
      <PickUpQuests />
      <TurnInQuests>
        <int>8650</int>
      </TurnInQuests>
      <Position X="2237.858" Y="-5340.407" Z="84.62836" Type="Flying" />
    </NPCQuest>
    <NPCQuest Id="15594" Name="Предок Лунная Заря" GameObject="false">
      <PickUpQuests />
      <TurnInQuests>
        <int>8714</int>
      </TurnInQuests>
      <Position X="1261.157" Y="-2558.268" Z="118.2072" Type="Flying" />
    </NPCQuest>
    <NPCQuest Id="15568" Name="Предок Могильный Холм" GameObject="false">
      <PickUpQuests />
      <TurnInQuests>
        <int>8652</int>
      </TurnInQuests>
      <Position X="2213.443" Y="237.8906" Z="33.58305" Type="Flying" />
    </NPCQuest>
    <NPCQuest Id="15564" Name="Предок Черносерд" GameObject="false">
      <PickUpQuests />
      <TurnInQuests>
        <int>8648</int>
      </TurnInQuests>
      <Position X="1633.303" Y="233.9314" Z="62.59161" />
    </NPCQuest>
    <NPCQuest Id="15561" Name="Предок Обсидиан" GameObject="false">
      <PickUpQuests />
      <TurnInQuests>
        <int>8645</int>
      </TurnInQuests>
      <Position X="514.7543" Y="1560.969" Z="130.0668" Type="Flying" />
    </NPCQuest>
  </NpcQuest>
  <Npc />
  <Blackspots />
  <BlackGuids />
  <EasyQuests>
    <EasyQuest>
      <Name>+To Eastern Kingdoms</Name>
      <QuestId />
      <QuestType>OverridePulseCSharpCode</QuestType>
      <QuestClass xsi:type="OverridePulseCSharpCodeEasyQuestClass">
        <Code>		if (ObjectManager.Me.IsAlliance)
		{
			Traveler.ToCapitalOpen();
		}
		else
		{
			Traveler.ToEasternKingdoms();
		}
		return true;</Code>
      </QuestClass>
      <ObjectiveCount1>0</ObjectiveCount1>
      <ObjectiveCount2>0</ObjectiveCount2>
      <ObjectiveCount3>0</ObjectiveCount3>
      <ObjectiveCount4>0</ObjectiveCount4>
      <ObjectiveCount5>0</ObjectiveCount5>
      <ObjectiveCount6>0</ObjectiveCount6>
      <ObjectiveCount7>0</ObjectiveCount7>
      <ObjectiveCount8>0</ObjectiveCount8>
      <ObjectiveCount9>0</ObjectiveCount9>
      <ObjectiveCount10>0</ObjectiveCount10>
      <AutoDetectObjectiveCount1>false</AutoDetectObjectiveCount1>
      <AutoDetectObjectiveCount2>false</AutoDetectObjectiveCount2>
      <AutoDetectObjectiveCount3>false</AutoDetectObjectiveCount3>
      <AutoDetectObjectiveCount4>false</AutoDetectObjectiveCount4>
      <AutoDetectObjectiveCount5>false</AutoDetectObjectiveCount5>
      <AutoDetectObjectiveCount6>false</AutoDetectObjectiveCount6>
      <AutoDetectObjectiveCount7>false</AutoDetectObjectiveCount7>
      <AutoDetectObjectiveCount8>false</AutoDetectObjectiveCount8>
      <AutoDetectObjectiveCount9>false</AutoDetectObjectiveCount9>
      <AutoDetectObjectiveCount10>false</AutoDetectObjectiveCount10>
      <CanCondition />
      <IsCompleteCondition>return Traveler.InEasternKingdoms &amp;&amp; !Traveler.InStormwindWizardsSanctum;</IsCompleteCondition>
      <RepeatableQuest>true</RepeatableQuest>
      <NotRequiredInQuestLog>true</NotRequiredInQuestLog>
      <PickUpQuestOnItem>false</PickUpQuestOnItem>
      <PickUpQuestOnItemID>0</PickUpQuestOnItemID>
      <Comment />
      <GossipOptionRewardItem>1</GossipOptionRewardItem>
      <RequiredQuest>0</RequiredQuest>
      <MaxLevel>999</MaxLevel>
      <MinLevel>0</MinLevel>
      <WoWClass>None</WoWClass>
    </EasyQuest>
    <EasyQuest>
      <Name>Time Travelling (Blasted Lands)</Name>
      <QuestId />
      <QuestType>InteractWithNpc</QuestType>
      <QuestClass xsi:type="InteractWithNpcEasyQuestClass">
        <HotSpots>
          <Vector3 X="-10761.14" Y="-2957.668" Z="58.74221" />
        </HotSpots>
        <GossipOptionNpcInteractWith>1</GossipOptionNpcInteractWith>
        <Macro />
        <IgnoreIfDead>false</IgnoreIfDead>
        <EntryIdTarget>
          <int>88206</int>
        </EntryIdTarget>
        <Range>4.5</Range>
      </QuestClass>
      <ObjectiveCount1>0</ObjectiveCount1>
      <ObjectiveCount2>0</ObjectiveCount2>
      <ObjectiveCount3>0</ObjectiveCount3>
      <ObjectiveCount4>0</ObjectiveCount4>
      <ObjectiveCount5>0</ObjectiveCount5>
      <ObjectiveCount6>0</ObjectiveCount6>
      <ObjectiveCount7>0</ObjectiveCount7>
      <ObjectiveCount8>0</ObjectiveCount8>
      <ObjectiveCount9>0</ObjectiveCount9>
      <ObjectiveCount10>0</ObjectiveCount10>
      <AutoDetectObjectiveCount1>false</AutoDetectObjectiveCount1>
      <AutoDetectObjectiveCount2>false</AutoDetectObjectiveCount2>
      <AutoDetectObjectiveCount3>false</AutoDetectObjectiveCount3>
      <AutoDetectObjectiveCount4>false</AutoDetectObjectiveCount4>
      <AutoDetectObjectiveCount5>false</AutoDetectObjectiveCount5>
      <AutoDetectObjectiveCount6>false</AutoDetectObjectiveCount6>
      <AutoDetectObjectiveCount7>false</AutoDetectObjectiveCount7>
      <AutoDetectObjectiveCount8>false</AutoDetectObjectiveCount8>
      <AutoDetectObjectiveCount9>false</AutoDetectObjectiveCount9>
      <AutoDetectObjectiveCount10>false</AutoDetectObjectiveCount10>
      <CanCondition />
      <IsCompleteCondition>return ObjectManager.Me.Level &lt; 90 || ObjectManager.Me.HaveBuff(176111) || Quest.GetQuestCompleted(8647);</IsCompleteCondition>
      <RepeatableQuest>true</RepeatableQuest>
      <NotRequiredInQuestLog>true</NotRequiredInQuestLog>
      <PickUpQuestOnItem>false</PickUpQuestOnItem>
      <PickUpQuestOnItemID>0</PickUpQuestOnItemID>
      <Comment />
      <GossipOptionRewardItem>1</GossipOptionRewardItem>
      <RequiredQuest>0</RequiredQuest>
      <MaxLevel>999</MaxLevel>
      <MinLevel>0</MinLevel>
      <WoWClass>None</WoWClass>
    </EasyQuest>
    <EasyQuest>
      <Name>Bellowrage the Elder</Name>
      <QuestId>
        <int>8647</int>
      </QuestId>
      <QuestType>None</QuestType>
      <QuestClass />
      <ObjectiveCount1>0</ObjectiveCount1>
      <ObjectiveCount2>0</ObjectiveCount2>
      <ObjectiveCount3>0</ObjectiveCount3>
      <ObjectiveCount4>0</ObjectiveCount4>
      <ObjectiveCount5>0</ObjectiveCount5>
      <ObjectiveCount6>0</ObjectiveCount6>
      <ObjectiveCount7>0</ObjectiveCount7>
      <ObjectiveCount8>0</ObjectiveCount8>
      <ObjectiveCount9>0</ObjectiveCount9>
      <ObjectiveCount10>0</ObjectiveCount10>
      <AutoDetectObjectiveCount1>false</AutoDetectObjectiveCount1>
      <AutoDetectObjectiveCount2>false</AutoDetectObjectiveCount2>
      <AutoDetectObjectiveCount3>false</AutoDetectObjectiveCount3>
      <AutoDetectObjectiveCount4>false</AutoDetectObjectiveCount4>
      <AutoDetectObjectiveCount5>false</AutoDetectObjectiveCount5>
      <AutoDetectObjectiveCount6>false</AutoDetectObjectiveCount6>
      <AutoDetectObjectiveCount7>false</AutoDetectObjectiveCount7>
      <AutoDetectObjectiveCount8>false</AutoDetectObjectiveCount8>
      <AutoDetectObjectiveCount9>false</AutoDetectObjectiveCount9>
      <AutoDetectObjectiveCount10>false</AutoDetectObjectiveCount10>
      <CanCondition />
      <IsCompleteCondition />
      <RepeatableQuest>false</RepeatableQuest>
      <NotRequiredInQuestLog>true</NotRequiredInQuestLog>
      <PickUpQuestOnItem>false</PickUpQuestOnItem>
      <PickUpQuestOnItemID>0</PickUpQuestOnItemID>
      <Comment />
      <GossipOptionRewardItem>1</GossipOptionRewardItem>
      <RequiredQuest>0</RequiredQuest>
      <MaxLevel>999</MaxLevel>
      <MinLevel>0</MinLevel>
      <WoWClass>None</WoWClass>
    </EasyQuest>
    <EasyQuest>
      <Name>Starglade the Elder</Name>
      <QuestId>
        <int>8716</int>
      </QuestId>
      <QuestType>None</QuestType>
      <QuestClass />
      <ObjectiveCount1>0</ObjectiveCount1>
      <ObjectiveCount2>0</ObjectiveCount2>
      <ObjectiveCount3>0</ObjectiveCount3>
      <ObjectiveCount4>0</ObjectiveCount4>
      <ObjectiveCount5>0</ObjectiveCount5>
      <ObjectiveCount6>0</ObjectiveCount6>
      <ObjectiveCount7>0</ObjectiveCount7>
      <ObjectiveCount8>0</ObjectiveCount8>
      <ObjectiveCount9>0</ObjectiveCount9>
      <ObjectiveCount10>0</ObjectiveCount10>
      <AutoDetectObjectiveCount1>false</AutoDetectObjectiveCount1>
      <AutoDetectObjectiveCount2>false</AutoDetectObjectiveCount2>
      <AutoDetectObjectiveCount3>false</AutoDetectObjectiveCount3>
      <AutoDetectObjectiveCount4>false</AutoDetectObjectiveCount4>
      <AutoDetectObjectiveCount5>false</AutoDetectObjectiveCount5>
      <AutoDetectObjectiveCount6>false</AutoDetectObjectiveCount6>
      <AutoDetectObjectiveCount7>false</AutoDetectObjectiveCount7>
      <AutoDetectObjectiveCount8>false</AutoDetectObjectiveCount8>
      <AutoDetectObjectiveCount9>false</AutoDetectObjectiveCount9>
      <AutoDetectObjectiveCount10>false</AutoDetectObjectiveCount10>
      <CanCondition />
      <IsCompleteCondition />
      <RepeatableQuest>false</RepeatableQuest>
      <NotRequiredInQuestLog>true</NotRequiredInQuestLog>
      <PickUpQuestOnItem>false</PickUpQuestOnItem>
      <PickUpQuestOnItemID>0</PickUpQuestOnItemID>
      <Comment />
      <GossipOptionRewardItem>1</GossipOptionRewardItem>
      <RequiredQuest>0</RequiredQuest>
      <MaxLevel>999</MaxLevel>
      <MinLevel>0</MinLevel>
      <WoWClass>None</WoWClass>
    </EasyQuest>
    <EasyQuest>
      <Name>Winterhoof the Elder</Name>
      <QuestId>
        <int>8674</int>
      </QuestId>
      <QuestType>None</QuestType>
      <QuestClass />
      <ObjectiveCount1>0</ObjectiveCount1>
      <ObjectiveCount2>0</ObjectiveCount2>
      <ObjectiveCount3>0</ObjectiveCount3>
      <ObjectiveCount4>0</ObjectiveCount4>
      <ObjectiveCount5>0</ObjectiveCount5>
      <ObjectiveCount6>0</ObjectiveCount6>
      <ObjectiveCount7>0</ObjectiveCount7>
      <ObjectiveCount8>0</ObjectiveCount8>
      <ObjectiveCount9>0</ObjectiveCount9>
      <ObjectiveCount10>0</ObjectiveCount10>
      <AutoDetectObjectiveCount1>false</AutoDetectObjectiveCount1>
      <AutoDetectObjectiveCount2>false</AutoDetectObjectiveCount2>
      <AutoDetectObjectiveCount3>false</AutoDetectObjectiveCount3>
      <AutoDetectObjectiveCount4>false</AutoDetectObjectiveCount4>
      <AutoDetectObjectiveCount5>false</AutoDetectObjectiveCount5>
      <AutoDetectObjectiveCount6>false</AutoDetectObjectiveCount6>
      <AutoDetectObjectiveCount7>false</AutoDetectObjectiveCount7>
      <AutoDetectObjectiveCount8>false</AutoDetectObjectiveCount8>
      <AutoDetectObjectiveCount9>false</AutoDetectObjectiveCount9>
      <AutoDetectObjectiveCount10>false</AutoDetectObjectiveCount10>
      <CanCondition />
      <IsCompleteCondition />
      <RepeatableQuest>false</RepeatableQuest>
      <NotRequiredInQuestLog>true</NotRequiredInQuestLog>
      <PickUpQuestOnItem>false</PickUpQuestOnItem>
      <PickUpQuestOnItemID>0</PickUpQuestOnItemID>
      <Comment />
      <GossipOptionRewardItem>1</GossipOptionRewardItem>
      <RequiredQuest>0</RequiredQuest>
      <MaxLevel>999</MaxLevel>
      <MinLevel>0</MinLevel>
      <WoWClass>None</WoWClass>
    </EasyQuest>
    <EasyQuest>
      <Name>Skychaser the Elder</Name>
      <QuestId>
        <int>8675</int>
      </QuestId>
      <QuestType>None</QuestType>
      <QuestClass />
      <ObjectiveCount1>0</ObjectiveCount1>
      <ObjectiveCount2>0</ObjectiveCount2>
      <ObjectiveCount3>0</ObjectiveCount3>
      <ObjectiveCount4>0</ObjectiveCount4>
      <ObjectiveCount5>0</ObjectiveCount5>
      <ObjectiveCount6>0</ObjectiveCount6>
      <ObjectiveCount7>0</ObjectiveCount7>
      <ObjectiveCount8>0</ObjectiveCount8>
      <ObjectiveCount9>0</ObjectiveCount9>
      <ObjectiveCount10>0</ObjectiveCount10>
      <AutoDetectObjectiveCount1>false</AutoDetectObjectiveCount1>
      <AutoDetectObjectiveCount2>false</AutoDetectObjectiveCount2>
      <AutoDetectObjectiveCount3>false</AutoDetectObjectiveCount3>
      <AutoDetectObjectiveCount4>false</AutoDetectObjectiveCount4>
      <AutoDetectObjectiveCount5>false</AutoDetectObjectiveCount5>
      <AutoDetectObjectiveCount6>false</AutoDetectObjectiveCount6>
      <AutoDetectObjectiveCount7>false</AutoDetectObjectiveCount7>
      <AutoDetectObjectiveCount8>false</AutoDetectObjectiveCount8>
      <AutoDetectObjectiveCount9>false</AutoDetectObjectiveCount9>
      <AutoDetectObjectiveCount10>false</AutoDetectObjectiveCount10>
      <CanCondition />
      <IsCompleteCondition />
      <RepeatableQuest>false</RepeatableQuest>
      <NotRequiredInQuestLog>true</NotRequiredInQuestLog>
      <PickUpQuestOnItem>false</PickUpQuestOnItem>
      <PickUpQuestOnItemID>0</PickUpQuestOnItemID>
      <Comment />
      <GossipOptionRewardItem>1</GossipOptionRewardItem>
      <RequiredQuest>0</RequiredQuest>
      <MaxLevel>999</MaxLevel>
      <MinLevel>0</MinLevel>
      <WoWClass>None</WoWClass>
    </EasyQuest>
    <EasyQuest>
      <Name>Stormbrow the Elder</Name>
      <QuestId>
        <int>8649</int>
      </QuestId>
      <QuestType>None</QuestType>
      <QuestClass />
      <ObjectiveCount1>0</ObjectiveCount1>
      <ObjectiveCount2>0</ObjectiveCount2>
      <ObjectiveCount3>0</ObjectiveCount3>
      <ObjectiveCount4>0</ObjectiveCount4>
      <ObjectiveCount5>0</ObjectiveCount5>
      <ObjectiveCount6>0</ObjectiveCount6>
      <ObjectiveCount7>0</ObjectiveCount7>
      <ObjectiveCount8>0</ObjectiveCount8>
      <ObjectiveCount9>0</ObjectiveCount9>
      <ObjectiveCount10>0</ObjectiveCount10>
      <AutoDetectObjectiveCount1>false</AutoDetectObjectiveCount1>
      <AutoDetectObjectiveCount2>false</AutoDetectObjectiveCount2>
      <AutoDetectObjectiveCount3>false</AutoDetectObjectiveCount3>
      <AutoDetectObjectiveCount4>false</AutoDetectObjectiveCount4>
      <AutoDetectObjectiveCount5>false</AutoDetectObjectiveCount5>
      <AutoDetectObjectiveCount6>false</AutoDetectObjectiveCount6>
      <AutoDetectObjectiveCount7>false</AutoDetectObjectiveCount7>
      <AutoDetectObjectiveCount8>false</AutoDetectObjectiveCount8>
      <AutoDetectObjectiveCount9>false</AutoDetectObjectiveCount9>
      <AutoDetectObjectiveCount10>false</AutoDetectObjectiveCount10>
      <CanCondition />
      <IsCompleteCondition />
      <RepeatableQuest>false</RepeatableQuest>
      <NotRequiredInQuestLog>true</NotRequiredInQuestLog>
      <PickUpQuestOnItem>false</PickUpQuestOnItem>
      <PickUpQuestOnItemID>0</PickUpQuestOnItemID>
      <Comment />
      <GossipOptionRewardItem>1</GossipOptionRewardItem>
      <RequiredQuest>0</RequiredQuest>
      <MaxLevel>999</MaxLevel>
      <MinLevel>0</MinLevel>
      <WoWClass>None</WoWClass>
    </EasyQuest>
    <EasyQuest>
      <Name>Hammershout the Elder</Name>
      <QuestId>
        <int>8646</int>
      </QuestId>
      <QuestType>None</QuestType>
      <QuestClass />
      <ObjectiveCount1>0</ObjectiveCount1>
      <ObjectiveCount2>0</ObjectiveCount2>
      <ObjectiveCount3>0</ObjectiveCount3>
      <ObjectiveCount4>0</ObjectiveCount4>
      <ObjectiveCount5>0</ObjectiveCount5>
      <ObjectiveCount6>0</ObjectiveCount6>
      <ObjectiveCount7>0</ObjectiveCount7>
      <ObjectiveCount8>0</ObjectiveCount8>
      <ObjectiveCount9>0</ObjectiveCount9>
      <ObjectiveCount10>0</ObjectiveCount10>
      <AutoDetectObjectiveCount1>false</AutoDetectObjectiveCount1>
      <AutoDetectObjectiveCount2>false</AutoDetectObjectiveCount2>
      <AutoDetectObjectiveCount3>false</AutoDetectObjectiveCount3>
      <AutoDetectObjectiveCount4>false</AutoDetectObjectiveCount4>
      <AutoDetectObjectiveCount5>false</AutoDetectObjectiveCount5>
      <AutoDetectObjectiveCount6>false</AutoDetectObjectiveCount6>
      <AutoDetectObjectiveCount7>false</AutoDetectObjectiveCount7>
      <AutoDetectObjectiveCount8>false</AutoDetectObjectiveCount8>
      <AutoDetectObjectiveCount9>false</AutoDetectObjectiveCount9>
      <AutoDetectObjectiveCount10>false</AutoDetectObjectiveCount10>
      <CanCondition />
      <IsCompleteCondition />
      <RepeatableQuest>false</RepeatableQuest>
      <NotRequiredInQuestLog>true</NotRequiredInQuestLog>
      <PickUpQuestOnItem>false</PickUpQuestOnItem>
      <PickUpQuestOnItemID>0</PickUpQuestOnItemID>
      <Comment />
      <GossipOptionRewardItem>1</GossipOptionRewardItem>
      <RequiredQuest>0</RequiredQuest>
      <MaxLevel>999</MaxLevel>
      <MinLevel>0</MinLevel>
      <WoWClass>None</WoWClass>
    </EasyQuest>
    <EasyQuest>
      <Name>Rumblerock the Elder</Name>
      <QuestId>
        <int>8636</int>
      </QuestId>
      <QuestType>None</QuestType>
      <QuestClass />
      <ObjectiveCount1>0</ObjectiveCount1>
      <ObjectiveCount2>0</ObjectiveCount2>
      <ObjectiveCount3>0</ObjectiveCount3>
      <ObjectiveCount4>0</ObjectiveCount4>
      <ObjectiveCount5>0</ObjectiveCount5>
      <ObjectiveCount6>0</ObjectiveCount6>
      <ObjectiveCount7>0</ObjectiveCount7>
      <ObjectiveCount8>0</ObjectiveCount8>
      <ObjectiveCount9>0</ObjectiveCount9>
      <ObjectiveCount10>0</ObjectiveCount10>
      <AutoDetectObjectiveCount1>false</AutoDetectObjectiveCount1>
      <AutoDetectObjectiveCount2>false</AutoDetectObjectiveCount2>
      <AutoDetectObjectiveCount3>false</AutoDetectObjectiveCount3>
      <AutoDetectObjectiveCount4>false</AutoDetectObjectiveCount4>
      <AutoDetectObjectiveCount5>false</AutoDetectObjectiveCount5>
      <AutoDetectObjectiveCount6>false</AutoDetectObjectiveCount6>
      <AutoDetectObjectiveCount7>false</AutoDetectObjectiveCount7>
      <AutoDetectObjectiveCount8>false</AutoDetectObjectiveCount8>
      <AutoDetectObjectiveCount9>false</AutoDetectObjectiveCount9>
      <AutoDetectObjectiveCount10>false</AutoDetectObjectiveCount10>
      <CanCondition />
      <IsCompleteCondition />
      <RepeatableQuest>false</RepeatableQuest>
      <NotRequiredInQuestLog>true</NotRequiredInQuestLog>
      <PickUpQuestOnItem>false</PickUpQuestOnItem>
      <PickUpQuestOnItemID>0</PickUpQuestOnItemID>
      <Comment />
      <GossipOptionRewardItem>1</GossipOptionRewardItem>
      <RequiredQuest>0</RequiredQuest>
      <MaxLevel>999</MaxLevel>
      <MinLevel>0</MinLevel>
      <WoWClass>None</WoWClass>
    </EasyQuest>
    <EasyQuest>
      <Name>Dawnstrider the Elder</Name>
      <QuestId>
        <int>8683</int>
      </QuestId>
      <QuestType>None</QuestType>
      <QuestClass />
      <ObjectiveCount1>0</ObjectiveCount1>
      <ObjectiveCount2>0</ObjectiveCount2>
      <ObjectiveCount3>0</ObjectiveCount3>
      <ObjectiveCount4>0</ObjectiveCount4>
      <ObjectiveCount5>0</ObjectiveCount5>
      <ObjectiveCount6>0</ObjectiveCount6>
      <ObjectiveCount7>0</ObjectiveCount7>
      <ObjectiveCount8>0</ObjectiveCount8>
      <ObjectiveCount9>0</ObjectiveCount9>
      <ObjectiveCount10>0</ObjectiveCount10>
      <AutoDetectObjectiveCount1>false</AutoDetectObjectiveCount1>
      <AutoDetectObjectiveCount2>false</AutoDetectObjectiveCount2>
      <AutoDetectObjectiveCount3>false</AutoDetectObjectiveCount3>
      <AutoDetectObjectiveCount4>false</AutoDetectObjectiveCount4>
      <AutoDetectObjectiveCount5>false</AutoDetectObjectiveCount5>
      <AutoDetectObjectiveCount6>false</AutoDetectObjectiveCount6>
      <AutoDetectObjectiveCount7>false</AutoDetectObjectiveCount7>
      <AutoDetectObjectiveCount8>false</AutoDetectObjectiveCount8>
      <AutoDetectObjectiveCount9>false</AutoDetectObjectiveCount9>
      <AutoDetectObjectiveCount10>false</AutoDetectObjectiveCount10>
      <CanCondition />
      <IsCompleteCondition />
      <RepeatableQuest>false</RepeatableQuest>
      <NotRequiredInQuestLog>true</NotRequiredInQuestLog>
      <PickUpQuestOnItem>false</PickUpQuestOnItem>
      <PickUpQuestOnItemID>0</PickUpQuestOnItemID>
      <Comment />
      <GossipOptionRewardItem>1</GossipOptionRewardItem>
      <RequiredQuest>0</RequiredQuest>
      <MaxLevel>999</MaxLevel>
      <MinLevel>0</MinLevel>
      <WoWClass>None</WoWClass>
    </EasyQuest>
    <EasyQuest>
      <Name>Goldwell the Elder</Name>
      <QuestId>
        <int>8653</int>
      </QuestId>
      <QuestType>None</QuestType>
      <QuestClass />
      <ObjectiveCount1>0</ObjectiveCount1>
      <ObjectiveCount2>0</ObjectiveCount2>
      <ObjectiveCount3>0</ObjectiveCount3>
      <ObjectiveCount4>0</ObjectiveCount4>
      <ObjectiveCount5>0</ObjectiveCount5>
      <ObjectiveCount6>0</ObjectiveCount6>
      <ObjectiveCount7>0</ObjectiveCount7>
      <ObjectiveCount8>0</ObjectiveCount8>
      <ObjectiveCount9>0</ObjectiveCount9>
      <ObjectiveCount10>0</ObjectiveCount10>
      <AutoDetectObjectiveCount1>false</AutoDetectObjectiveCount1>
      <AutoDetectObjectiveCount2>false</AutoDetectObjectiveCount2>
      <AutoDetectObjectiveCount3>false</AutoDetectObjectiveCount3>
      <AutoDetectObjectiveCount4>false</AutoDetectObjectiveCount4>
      <AutoDetectObjectiveCount5>false</AutoDetectObjectiveCount5>
      <AutoDetectObjectiveCount6>false</AutoDetectObjectiveCount6>
      <AutoDetectObjectiveCount7>false</AutoDetectObjectiveCount7>
      <AutoDetectObjectiveCount8>false</AutoDetectObjectiveCount8>
      <AutoDetectObjectiveCount9>false</AutoDetectObjectiveCount9>
      <AutoDetectObjectiveCount10>false</AutoDetectObjectiveCount10>
      <CanCondition />
      <IsCompleteCondition />
      <RepeatableQuest>false</RepeatableQuest>
      <NotRequiredInQuestLog>true</NotRequiredInQuestLog>
      <PickUpQuestOnItem>false</PickUpQuestOnItem>
      <PickUpQuestOnItemID>0</PickUpQuestOnItemID>
      <Comment />
      <GossipOptionRewardItem>1</GossipOptionRewardItem>
      <RequiredQuest>0</RequiredQuest>
      <MaxLevel>999</MaxLevel>
      <MinLevel>0</MinLevel>
      <WoWClass>None</WoWClass>
    </EasyQuest>
    <EasyQuest>
      <Name>Silvervein the Elder</Name>
      <QuestId>
        <int>8642</int>
      </QuestId>
      <QuestType>None</QuestType>
      <QuestClass />
      <ObjectiveCount1>0</ObjectiveCount1>
      <ObjectiveCount2>0</ObjectiveCount2>
      <ObjectiveCount3>0</ObjectiveCount3>
      <ObjectiveCount4>0</ObjectiveCount4>
      <ObjectiveCount5>0</ObjectiveCount5>
      <ObjectiveCount6>0</ObjectiveCount6>
      <ObjectiveCount7>0</ObjectiveCount7>
      <ObjectiveCount8>0</ObjectiveCount8>
      <ObjectiveCount9>0</ObjectiveCount9>
      <ObjectiveCount10>0</ObjectiveCount10>
      <AutoDetectObjectiveCount1>false</AutoDetectObjectiveCount1>
      <AutoDetectObjectiveCount2>false</AutoDetectObjectiveCount2>
      <AutoDetectObjectiveCount3>false</AutoDetectObjectiveCount3>
      <AutoDetectObjectiveCount4>false</AutoDetectObjectiveCount4>
      <AutoDetectObjectiveCount5>false</AutoDetectObjectiveCount5>
      <AutoDetectObjectiveCount6>false</AutoDetectObjectiveCount6>
      <AutoDetectObjectiveCount7>false</AutoDetectObjectiveCount7>
      <AutoDetectObjectiveCount8>false</AutoDetectObjectiveCount8>
      <AutoDetectObjectiveCount9>false</AutoDetectObjectiveCount9>
      <AutoDetectObjectiveCount10>false</AutoDetectObjectiveCount10>
      <CanCondition />
      <IsCompleteCondition />
      <RepeatableQuest>false</RepeatableQuest>
      <NotRequiredInQuestLog>true</NotRequiredInQuestLog>
      <PickUpQuestOnItem>false</PickUpQuestOnItem>
      <PickUpQuestOnItemID>0</PickUpQuestOnItemID>
      <Comment />
      <GossipOptionRewardItem>1</GossipOptionRewardItem>
      <RequiredQuest>0</RequiredQuest>
      <MaxLevel>999</MaxLevel>
      <MinLevel>0</MinLevel>
      <WoWClass>None</WoWClass>
    </EasyQuest>
    <EasyQuest>
      <Name>Firebeard the Elder</Name>
      <QuestId>
        <int>29737</int>
      </QuestId>
      <QuestType>None</QuestType>
      <QuestClass />
      <ObjectiveCount1>0</ObjectiveCount1>
      <ObjectiveCount2>0</ObjectiveCount2>
      <ObjectiveCount3>0</ObjectiveCount3>
      <ObjectiveCount4>0</ObjectiveCount4>
      <ObjectiveCount5>0</ObjectiveCount5>
      <ObjectiveCount6>0</ObjectiveCount6>
      <ObjectiveCount7>0</ObjectiveCount7>
      <ObjectiveCount8>0</ObjectiveCount8>
      <ObjectiveCount9>0</ObjectiveCount9>
      <ObjectiveCount10>0</ObjectiveCount10>
      <AutoDetectObjectiveCount1>false</AutoDetectObjectiveCount1>
      <AutoDetectObjectiveCount2>false</AutoDetectObjectiveCount2>
      <AutoDetectObjectiveCount3>false</AutoDetectObjectiveCount3>
      <AutoDetectObjectiveCount4>false</AutoDetectObjectiveCount4>
      <AutoDetectObjectiveCount5>false</AutoDetectObjectiveCount5>
      <AutoDetectObjectiveCount6>false</AutoDetectObjectiveCount6>
      <AutoDetectObjectiveCount7>false</AutoDetectObjectiveCount7>
      <AutoDetectObjectiveCount8>false</AutoDetectObjectiveCount8>
      <AutoDetectObjectiveCount9>false</AutoDetectObjectiveCount9>
      <AutoDetectObjectiveCount10>false</AutoDetectObjectiveCount10>
      <CanCondition />
      <IsCompleteCondition />
      <RepeatableQuest>false</RepeatableQuest>
      <NotRequiredInQuestLog>true</NotRequiredInQuestLog>
      <PickUpQuestOnItem>false</PickUpQuestOnItem>
      <PickUpQuestOnItemID>0</PickUpQuestOnItemID>
      <Comment />
      <GossipOptionRewardItem>1</GossipOptionRewardItem>
      <RequiredQuest>0</RequiredQuest>
      <MaxLevel>999</MaxLevel>
      <MinLevel>0</MinLevel>
      <WoWClass>None</WoWClass>
    </EasyQuest>
    <EasyQuest>
      <Name>Darkfeather the Elder</Name>
      <QuestId>
        <int>29736</int>
      </QuestId>
      <QuestType>None</QuestType>
      <QuestClass />
      <ObjectiveCount1>0</ObjectiveCount1>
      <ObjectiveCount2>0</ObjectiveCount2>
      <ObjectiveCount3>0</ObjectiveCount3>
      <ObjectiveCount4>0</ObjectiveCount4>
      <ObjectiveCount5>0</ObjectiveCount5>
      <ObjectiveCount6>0</ObjectiveCount6>
      <ObjectiveCount7>0</ObjectiveCount7>
      <ObjectiveCount8>0</ObjectiveCount8>
      <ObjectiveCount9>0</ObjectiveCount9>
      <ObjectiveCount10>0</ObjectiveCount10>
      <AutoDetectObjectiveCount1>false</AutoDetectObjectiveCount1>
      <AutoDetectObjectiveCount2>false</AutoDetectObjectiveCount2>
      <AutoDetectObjectiveCount3>false</AutoDetectObjectiveCount3>
      <AutoDetectObjectiveCount4>false</AutoDetectObjectiveCount4>
      <AutoDetectObjectiveCount5>false</AutoDetectObjectiveCount5>
      <AutoDetectObjectiveCount6>false</AutoDetectObjectiveCount6>
      <AutoDetectObjectiveCount7>false</AutoDetectObjectiveCount7>
      <AutoDetectObjectiveCount8>false</AutoDetectObjectiveCount8>
      <AutoDetectObjectiveCount9>false</AutoDetectObjectiveCount9>
      <AutoDetectObjectiveCount10>false</AutoDetectObjectiveCount10>
      <CanCondition />
      <IsCompleteCondition />
      <RepeatableQuest>false</RepeatableQuest>
      <NotRequiredInQuestLog>true</NotRequiredInQuestLog>
      <PickUpQuestOnItem>false</PickUpQuestOnItem>
      <PickUpQuestOnItemID>0</PickUpQuestOnItemID>
      <Comment />
      <GossipOptionRewardItem>1</GossipOptionRewardItem>
      <RequiredQuest>0</RequiredQuest>
      <MaxLevel>999</MaxLevel>
      <MinLevel>0</MinLevel>
      <WoWClass>None</WoWClass>
    </EasyQuest>
    <EasyQuest>
      <Name>Highpeak the Elder</Name>
      <QuestId>
        <int>8643</int>
      </QuestId>
      <QuestType>None</QuestType>
      <QuestClass />
      <ObjectiveCount1>0</ObjectiveCount1>
      <ObjectiveCount2>0</ObjectiveCount2>
      <ObjectiveCount3>0</ObjectiveCount3>
      <ObjectiveCount4>0</ObjectiveCount4>
      <ObjectiveCount5>0</ObjectiveCount5>
      <ObjectiveCount6>0</ObjectiveCount6>
      <ObjectiveCount7>0</ObjectiveCount7>
      <ObjectiveCount8>0</ObjectiveCount8>
      <ObjectiveCount9>0</ObjectiveCount9>
      <ObjectiveCount10>0</ObjectiveCount10>
      <AutoDetectObjectiveCount1>false</AutoDetectObjectiveCount1>
      <AutoDetectObjectiveCount2>false</AutoDetectObjectiveCount2>
      <AutoDetectObjectiveCount3>false</AutoDetectObjectiveCount3>
      <AutoDetectObjectiveCount4>false</AutoDetectObjectiveCount4>
      <AutoDetectObjectiveCount5>false</AutoDetectObjectiveCount5>
      <AutoDetectObjectiveCount6>false</AutoDetectObjectiveCount6>
      <AutoDetectObjectiveCount7>false</AutoDetectObjectiveCount7>
      <AutoDetectObjectiveCount8>false</AutoDetectObjectiveCount8>
      <AutoDetectObjectiveCount9>false</AutoDetectObjectiveCount9>
      <AutoDetectObjectiveCount10>false</AutoDetectObjectiveCount10>
      <CanCondition />
      <IsCompleteCondition />
      <RepeatableQuest>false</RepeatableQuest>
      <NotRequiredInQuestLog>true</NotRequiredInQuestLog>
      <PickUpQuestOnItem>false</PickUpQuestOnItem>
      <PickUpQuestOnItemID>0</PickUpQuestOnItemID>
      <Comment />
      <GossipOptionRewardItem>1</GossipOptionRewardItem>
      <RequiredQuest>0</RequiredQuest>
      <MaxLevel>999</MaxLevel>
      <MinLevel>0</MinLevel>
      <WoWClass>None</WoWClass>
    </EasyQuest>
    <EasyQuest>
      <Name>Snowcrown the Elder</Name>
      <QuestId>
        <int>8650</int>
      </QuestId>
      <QuestType>None</QuestType>
      <QuestClass />
      <ObjectiveCount1>0</ObjectiveCount1>
      <ObjectiveCount2>0</ObjectiveCount2>
      <ObjectiveCount3>0</ObjectiveCount3>
      <ObjectiveCount4>0</ObjectiveCount4>
      <ObjectiveCount5>0</ObjectiveCount5>
      <ObjectiveCount6>0</ObjectiveCount6>
      <ObjectiveCount7>0</ObjectiveCount7>
      <ObjectiveCount8>0</ObjectiveCount8>
      <ObjectiveCount9>0</ObjectiveCount9>
      <ObjectiveCount10>0</ObjectiveCount10>
      <AutoDetectObjectiveCount1>false</AutoDetectObjectiveCount1>
      <AutoDetectObjectiveCount2>false</AutoDetectObjectiveCount2>
      <AutoDetectObjectiveCount3>false</AutoDetectObjectiveCount3>
      <AutoDetectObjectiveCount4>false</AutoDetectObjectiveCount4>
      <AutoDetectObjectiveCount5>false</AutoDetectObjectiveCount5>
      <AutoDetectObjectiveCount6>false</AutoDetectObjectiveCount6>
      <AutoDetectObjectiveCount7>false</AutoDetectObjectiveCount7>
      <AutoDetectObjectiveCount8>false</AutoDetectObjectiveCount8>
      <AutoDetectObjectiveCount9>false</AutoDetectObjectiveCount9>
      <AutoDetectObjectiveCount10>false</AutoDetectObjectiveCount10>
      <CanCondition />
      <IsCompleteCondition />
      <RepeatableQuest>false</RepeatableQuest>
      <NotRequiredInQuestLog>true</NotRequiredInQuestLog>
      <PickUpQuestOnItem>false</PickUpQuestOnItem>
      <PickUpQuestOnItemID>0</PickUpQuestOnItemID>
      <Comment />
      <GossipOptionRewardItem>1</GossipOptionRewardItem>
      <RequiredQuest>0</RequiredQuest>
      <MaxLevel>999</MaxLevel>
      <MinLevel>0</MinLevel>
      <WoWClass>None</WoWClass>
    </EasyQuest>
    <EasyQuest>
      <Name>Moonstrike the Elder</Name>
      <QuestId>
        <int>8714</int>
      </QuestId>
      <QuestType>None</QuestType>
      <QuestClass />
      <ObjectiveCount1>0</ObjectiveCount1>
      <ObjectiveCount2>0</ObjectiveCount2>
      <ObjectiveCount3>0</ObjectiveCount3>
      <ObjectiveCount4>0</ObjectiveCount4>
      <ObjectiveCount5>0</ObjectiveCount5>
      <ObjectiveCount6>0</ObjectiveCount6>
      <ObjectiveCount7>0</ObjectiveCount7>
      <ObjectiveCount8>0</ObjectiveCount8>
      <ObjectiveCount9>0</ObjectiveCount9>
      <ObjectiveCount10>0</ObjectiveCount10>
      <AutoDetectObjectiveCount1>false</AutoDetectObjectiveCount1>
      <AutoDetectObjectiveCount2>false</AutoDetectObjectiveCount2>
      <AutoDetectObjectiveCount3>false</AutoDetectObjectiveCount3>
      <AutoDetectObjectiveCount4>false</AutoDetectObjectiveCount4>
      <AutoDetectObjectiveCount5>false</AutoDetectObjectiveCount5>
      <AutoDetectObjectiveCount6>false</AutoDetectObjectiveCount6>
      <AutoDetectObjectiveCount7>false</AutoDetectObjectiveCount7>
      <AutoDetectObjectiveCount8>false</AutoDetectObjectiveCount8>
      <AutoDetectObjectiveCount9>false</AutoDetectObjectiveCount9>
      <AutoDetectObjectiveCount10>false</AutoDetectObjectiveCount10>
      <CanCondition />
      <IsCompleteCondition />
      <RepeatableQuest>false</RepeatableQuest>
      <NotRequiredInQuestLog>true</NotRequiredInQuestLog>
      <PickUpQuestOnItem>false</PickUpQuestOnItem>
      <PickUpQuestOnItemID>0</PickUpQuestOnItemID>
      <Comment />
      <GossipOptionRewardItem>1</GossipOptionRewardItem>
      <RequiredQuest>0</RequiredQuest>
      <MaxLevel>999</MaxLevel>
      <MinLevel>0</MinLevel>
      <WoWClass>None</WoWClass>
    </EasyQuest>
    <EasyQuest>
      <Name>Graveborn the Elder</Name>
      <QuestId>
        <int>8652</int>
      </QuestId>
      <QuestType>None</QuestType>
      <QuestClass />
      <ObjectiveCount1>0</ObjectiveCount1>
      <ObjectiveCount2>0</ObjectiveCount2>
      <ObjectiveCount3>0</ObjectiveCount3>
      <ObjectiveCount4>0</ObjectiveCount4>
      <ObjectiveCount5>0</ObjectiveCount5>
      <ObjectiveCount6>0</ObjectiveCount6>
      <ObjectiveCount7>0</ObjectiveCount7>
      <ObjectiveCount8>0</ObjectiveCount8>
      <ObjectiveCount9>0</ObjectiveCount9>
      <ObjectiveCount10>0</ObjectiveCount10>
      <AutoDetectObjectiveCount1>false</AutoDetectObjectiveCount1>
      <AutoDetectObjectiveCount2>false</AutoDetectObjectiveCount2>
      <AutoDetectObjectiveCount3>false</AutoDetectObjectiveCount3>
      <AutoDetectObjectiveCount4>false</AutoDetectObjectiveCount4>
      <AutoDetectObjectiveCount5>false</AutoDetectObjectiveCount5>
      <AutoDetectObjectiveCount6>false</AutoDetectObjectiveCount6>
      <AutoDetectObjectiveCount7>false</AutoDetectObjectiveCount7>
      <AutoDetectObjectiveCount8>false</AutoDetectObjectiveCount8>
      <AutoDetectObjectiveCount9>false</AutoDetectObjectiveCount9>
      <AutoDetectObjectiveCount10>false</AutoDetectObjectiveCount10>
      <CanCondition />
      <IsCompleteCondition />
      <RepeatableQuest>false</RepeatableQuest>
      <NotRequiredInQuestLog>true</NotRequiredInQuestLog>
      <PickUpQuestOnItem>false</PickUpQuestOnItem>
      <PickUpQuestOnItemID>0</PickUpQuestOnItemID>
      <Comment />
      <GossipOptionRewardItem>1</GossipOptionRewardItem>
      <RequiredQuest>0</RequiredQuest>
      <MaxLevel>999</MaxLevel>
      <MinLevel>0</MinLevel>
      <WoWClass>None</WoWClass>
    </EasyQuest>
    <EasyQuest>
      <Name>Darkcore the Elder</Name>
      <QuestId>
        <int>8648</int>
      </QuestId>
      <QuestType>None</QuestType>
      <QuestClass />
      <ObjectiveCount1>0</ObjectiveCount1>
      <ObjectiveCount2>0</ObjectiveCount2>
      <ObjectiveCount3>0</ObjectiveCount3>
      <ObjectiveCount4>0</ObjectiveCount4>
      <ObjectiveCount5>0</ObjectiveCount5>
      <ObjectiveCount6>0</ObjectiveCount6>
      <ObjectiveCount7>0</ObjectiveCount7>
      <ObjectiveCount8>0</ObjectiveCount8>
      <ObjectiveCount9>0</ObjectiveCount9>
      <ObjectiveCount10>0</ObjectiveCount10>
      <AutoDetectObjectiveCount1>false</AutoDetectObjectiveCount1>
      <AutoDetectObjectiveCount2>false</AutoDetectObjectiveCount2>
      <AutoDetectObjectiveCount3>false</AutoDetectObjectiveCount3>
      <AutoDetectObjectiveCount4>false</AutoDetectObjectiveCount4>
      <AutoDetectObjectiveCount5>false</AutoDetectObjectiveCount5>
      <AutoDetectObjectiveCount6>false</AutoDetectObjectiveCount6>
      <AutoDetectObjectiveCount7>false</AutoDetectObjectiveCount7>
      <AutoDetectObjectiveCount8>false</AutoDetectObjectiveCount8>
      <AutoDetectObjectiveCount9>false</AutoDetectObjectiveCount9>
      <AutoDetectObjectiveCount10>false</AutoDetectObjectiveCount10>
      <CanCondition />
      <IsCompleteCondition />
      <RepeatableQuest>false</RepeatableQuest>
      <NotRequiredInQuestLog>true</NotRequiredInQuestLog>
      <PickUpQuestOnItem>false</PickUpQuestOnItem>
      <PickUpQuestOnItemID>0</PickUpQuestOnItemID>
      <Comment />
      <GossipOptionRewardItem>1</GossipOptionRewardItem>
      <RequiredQuest>0</RequiredQuest>
      <MaxLevel>999</MaxLevel>
      <MinLevel>0</MinLevel>
      <WoWClass>None</WoWClass>
    </EasyQuest>
    <EasyQuest>
      <Name>Obsidian the Elder</Name>
      <QuestId>
        <int>8645</int>
      </QuestId>
      <QuestType>None</QuestType>
      <QuestClass />
      <ObjectiveCount1>0</ObjectiveCount1>
      <ObjectiveCount2>0</ObjectiveCount2>
      <ObjectiveCount3>0</ObjectiveCount3>
      <ObjectiveCount4>0</ObjectiveCount4>
      <ObjectiveCount5>0</ObjectiveCount5>
      <ObjectiveCount6>0</ObjectiveCount6>
      <ObjectiveCount7>0</ObjectiveCount7>
      <ObjectiveCount8>0</ObjectiveCount8>
      <ObjectiveCount9>0</ObjectiveCount9>
      <ObjectiveCount10>0</ObjectiveCount10>
      <AutoDetectObjectiveCount1>false</AutoDetectObjectiveCount1>
      <AutoDetectObjectiveCount2>false</AutoDetectObjectiveCount2>
      <AutoDetectObjectiveCount3>false</AutoDetectObjectiveCount3>
      <AutoDetectObjectiveCount4>false</AutoDetectObjectiveCount4>
      <AutoDetectObjectiveCount5>false</AutoDetectObjectiveCount5>
      <AutoDetectObjectiveCount6>false</AutoDetectObjectiveCount6>
      <AutoDetectObjectiveCount7>false</AutoDetectObjectiveCount7>
      <AutoDetectObjectiveCount8>false</AutoDetectObjectiveCount8>
      <AutoDetectObjectiveCount9>false</AutoDetectObjectiveCount9>
      <AutoDetectObjectiveCount10>false</AutoDetectObjectiveCount10>
      <CanCondition />
      <IsCompleteCondition />
      <RepeatableQuest>false</RepeatableQuest>
      <NotRequiredInQuestLog>true</NotRequiredInQuestLog>
      <PickUpQuestOnItem>false</PickUpQuestOnItem>
      <PickUpQuestOnItemID>0</PickUpQuestOnItemID>
      <Comment />
      <GossipOptionRewardItem>1</GossipOptionRewardItem>
      <RequiredQuest>0</RequiredQuest>
      <MaxLevel>999</MaxLevel>
      <MinLevel>0</MinLevel>
      <WoWClass>None</WoWClass>
    </EasyQuest>
  </EasyQuests>
  <Script>camelot10\Libs\Questing.cs
camelot10\Libs\Traveler.cs</Script>
  <OffMeshConnections />
</EasyQuestProfile>